src/counter.v
module counter #( parameter WIDTH=4)
	(
		input rst, en,clk, up_down,
	output reg [WIDTH-1:0] count
);
always@(posedge clk) begin
	if(rst)
		count<=0;
	else if(en)begin
		if(up_down)
			count<=count+1;
		else
			count<=count-1;
	end
	else
		count<=count;
end
endmodule

tb/counter_tb.v
module counter_tb;
parameter WIDTH=4;
reg rst;
reg en;
reg clk;
reg up_down;
wire [WIDTH-1:0] count;

counter uut(
	.rst(rst),
	.en(en),
	.clk(clk),
	.up_down(up_down),
	.count(count)
);

always #5 clk=~clk;
initial begin
	clk=0;
	$monitor("Time=%0t \t clk=%b \t reset=%b \t enable=%b \t up_down=%b \t count=%b", $time,clk,rst,en,up_down,count);
	rst=1; en=1; up_down=1; #10;
	rst=0; #10;
	en=0; #5;
	rst=1; #10;
	rst=0; en=1; #30;
	up_down=0; #100;
	$finish;
end

initial begin
	$dumpfile("counter.vcd");
	$dumpvars();
end
endmodule

waveform/counter.vcd
$date
	Wed Jul 16 16:15:16 2025
$end
$version
	Icarus Verilog
$end
$timescale
	1s
$end
$scope module counter_tb $end
$var wire 4 ! count [3:0] $end
$var reg 1 " clk $end
$var reg 1 # en $end
$var reg 1 $ rst $end
$var reg 1 % up_down $end
$scope module uut $end
$var wire 1 " clk $end
$var wire 1 # en $end
$var wire 1 $ rst $end
$var wire 1 % up_down $end
$var reg 4 & count [3:0] $end
$upscope $end
$upscope $end
$enddefinitions $end
#0
$dumpvars
bx &
1%
1$
1#
0"
bx !
$end
#5
b0 !
b0 &
1"
#10
0"
0$
#15
b1 !
b1 &
1"
#20
0"
0#
#25
b0 !
b0 &
1"
1$
#30
0"
#35
b1 !
b1 &
1"
1#
0$
#40
0"
#45
b10 !
b10 &
1"
#50
0"
#55
b11 !
b11 &
1"
#60
0"
#65
b10 !
b10 &
1"
0%
#70
0"
#75
b1 !
b1 &
1"
#80
0"
#85
b0 !
b0 &
1"
#90
0"
#95
b1111 !
b1111 &
1"
#100
0"
#105
b1110 !
b1110 &
1"
#110
0"
#115
b1101 !
b1101 &
1"
#120
0"
#125
b1100 !
b1100 &
1"
#130
0"
#135
b1011 !
b1011 &
1"
#140
0"
#145
b1010 !
b1010 &
1"
#150
0"
#155
b1001 !
b1001 &
1"
#160
0"
#165
b1000 !
b1000 &
1"
